pyresample/__init__.py
pyresample/_caching.py
pyresample/_compat.py
pyresample/_config.py
pyresample/_formatting_html.py
pyresample/_multi_proc.py
pyresample/_spatial_mp.py
pyresample/area_config.py
pyresample/data_reduce.py
pyresample/geo_filter.py
pyresample/geometry.py
pyresample/grid.py
pyresample/image.py
pyresample/kd_tree.py
pyresample/plot.py
pyresample/py.typed
pyresample/resampler.py
pyresample/slicer.py
pyresample/spherical.py
pyresample/spherical_geometry.py
pyresample/spherical_utils.py
pyresample/version.py
pyresample/bilinear/__init__.py
pyresample/bilinear/_base.py
pyresample/bilinear/_numpy_resampler.py
pyresample/bilinear/xarr.py
pyresample/boundary/__init__.py
pyresample/boundary/legacy_boundary.py
pyresample/bucket/__init__.py
pyresample/ewa/__init__.py
pyresample/ewa/_fornav.cp313-win_amd64.pyd
pyresample/ewa/_fornav.pyx
pyresample/ewa/_fornav_templates.cpp
pyresample/ewa/_fornav_templates.h
pyresample/ewa/_legacy_dask_ewa.py
pyresample/ewa/_ll2cr.cp313-win_amd64.pyd
pyresample/ewa/_ll2cr.pyx
pyresample/ewa/dask_ewa.py
pyresample/ewa/ewa.py
pyresample/future/__init__.py
pyresample/future/geometry/__init__.py
pyresample/future/geometry/_subset.py
pyresample/future/geometry/area.py
pyresample/future/geometry/base.py
pyresample/future/geometry/swath.py
pyresample/future/resamplers/__init__.py
pyresample/future/resamplers/_transform_utils.py
pyresample/future/resamplers/nearest.py
pyresample/future/resamplers/registry.py
pyresample/future/resamplers/resampler.py
pyresample/future/spherical/__init__.py
pyresample/future/spherical/point.py
pyresample/gradient/__init__.py
pyresample/gradient/_gradient_search.cp313-win_amd64.pyd
pyresample/gradient/_gradient_search.pyx
pyresample/static/__init__.py
pyresample/static/css/__init__.py
pyresample/static/css/style.css
pyresample/static/html/__init__.py
pyresample/static/html/icons_svg_inline.html
pyresample/test/__init__.py
pyresample/test/conftest.py
pyresample/test/test_area_config.py
pyresample-1.34.2.dist-info/licenses/LICENSE.txt
pyresample-1.34.2.dist-info/METADATA
pyresample-1.34.2.dist-info/WHEEL
pyresample-1.34.2.dist-info/entry_points.txt
pyresample-1.34.2.dist-info/top_level.txt
pyresample-1.34.2.dist-info/RECORD
