Metadata-Version: 2.4
Name: pyresample
Version: 1.34.2
Summary: Geospatial image resampling in Python
Home-page: https://github.com/pytroll/pyresample
Author: Thomas Lavergne
Author-email: t.lavergne@met.no
Classifier: Development Status :: 5 - Production/Stable
Classifier: License :: OSI Approved :: GNU Lesser General Public License v3 or later (LGPLv3+)
Classifier: Programming Language :: Python
Classifier: Programming Language :: Cython
Classifier: Operating System :: OS Independent
Classifier: Intended Audience :: Science/Research
Classifier: Topic :: Scientific/Engineering
Requires-Python: >=3.11
License-File: LICENSE.txt
Requires-Dist: pyproj>=3.0
Requires-Dist: configobj
Requires-Dist: pykdtree>=1.3.1
Requires-Dist: pyyaml
Requires-Dist: numpy>=1.21.0
Requires-Dist: shapely
Requires-Dist: donfig
Requires-Dist: platformdirs
Provides-Extra: numexpr
Requires-Dist: numexpr; extra == "numexpr"
Provides-Extra: quicklook
Requires-Dist: matplotlib; extra == "quicklook"
Requires-Dist: cartopy>=0.20.0; extra == "quicklook"
Requires-Dist: pillow; extra == "quicklook"
Provides-Extra: rasterio
Requires-Dist: rasterio; extra == "rasterio"
Provides-Extra: dask
Requires-Dist: dask>=0.16.1; extra == "dask"
Provides-Extra: cf
Requires-Dist: xarray; extra == "cf"
Provides-Extra: gradient-search
Requires-Dist: shapely; extra == "gradient-search"
Provides-Extra: xarray-bilinear
Requires-Dist: xarray; extra == "xarray-bilinear"
Requires-Dist: dask; extra == "xarray-bilinear"
Requires-Dist: zarr; extra == "xarray-bilinear"
Provides-Extra: odc-geo
Requires-Dist: odc-geo; extra == "odc-geo"
Provides-Extra: tests
Requires-Dist: rasterio; extra == "tests"
Requires-Dist: dask; extra == "tests"
Requires-Dist: xarray; extra == "tests"
Requires-Dist: cartopy>=0.20.0; extra == "tests"
Requires-Dist: pillow; extra == "tests"
Requires-Dist: matplotlib; extra == "tests"
Requires-Dist: scipy; extra == "tests"
Requires-Dist: zarr; extra == "tests"
Requires-Dist: pytest-lazy-fixtures; extra == "tests"
Requires-Dist: shapely; extra == "tests"
Requires-Dist: odc-geo; extra == "tests"
Provides-Extra: all
Requires-Dist: zarr; extra == "all"
Requires-Dist: pillow; extra == "all"
Requires-Dist: cartopy>=0.20.0; extra == "all"
Requires-Dist: numexpr; extra == "all"
Requires-Dist: matplotlib; extra == "all"
Requires-Dist: shapely; extra == "all"
Requires-Dist: scipy; extra == "all"
Requires-Dist: pytest-lazy-fixtures; extra == "all"
Requires-Dist: xarray; extra == "all"
Requires-Dist: dask; extra == "all"
Requires-Dist: rasterio; extra == "all"
Requires-Dist: dask>=0.16.1; extra == "all"
Requires-Dist: odc-geo; extra == "all"
Dynamic: author
Dynamic: author-email
Dynamic: classifier
Dynamic: description
Dynamic: description-content-type
Dynamic: home-page
Dynamic: license-file
Dynamic: provides-extra
Dynamic: requires-dist
Dynamic: requires-python
Dynamic: summary
